{
  "assets" : {
    "4A1547C44D2F609A82737A690921C3FB" : {
      "type" : "texture",
      "index" : 2,
      "assetRequest" : {
        "type" : "slide",
        "state" : "contents",
        "slide" : "none"
      },
      "url" : {
        "native" : "assets\/E42D39F1-91E2-4E28-B0A5-E431EC188862.pdf"
      },
      "width" : 904,
      "height" : 685
    },
    "D0D8472915A570F5F53611B33B594150" : {
      "type" : "texture",
      "index" : 1,
      "assetRequest" : {
        "type" : "slide",
        "state" : "contents",
        "slide" : "none"
      },
      "url" : {
        "native" : "assets\/E42D39F1-91E2-4E28-B0A5-E431EC188862.pdf"
      },
      "width" : 824,
      "height" : 198
    },
    "FBB5DEA59905EE30EF2803B0A74DF992" : {
      "type" : "texture",
      "index" : 0,
      "assetRequest" : {
        "type" : "slide",
        "state" : "contents",
        "slide" : "none"
      },
      "url" : {
        "native" : "assets\/E42D39F1-91E2-4E28-B0A5-E431EC188862.pdf"
      },
      "width" : 1024,
      "height" : 768
    },
    "864A7B7723CE1A8CF60C01BEC0876FB0" : {
      "type" : "texture",
      "index" : 3,
      "assetRequest" : {
        "type" : "slide",
        "state" : "contents",
        "slide" : "none"
      },
      "url" : {
        "native" : "assets\/E42D39F1-91E2-4E28-B0A5-E431EC188862.pdf"
      },
      "width" : 61,
      "height" : 25
    },
    "48119D83BDF27884EA3D9E61FE2DAACC" : {
      "type" : "texture",
      "index" : 4,
      "assetRequest" : {
        "type" : "slide",
        "state" : "contents",
        "slide" : "none"
      },
      "url" : {
        "native" : "assets\/E42D39F1-91E2-4E28-B0A5-E431EC188862.pdf"
      },
      "width" : 1024,
      "height" : 768
    },
    "B64F7886CD8D2F544D0273D8C8664C9C" : {
      "type" : "texture",
      "index" : 5,
      "assetRequest" : {
        "type" : "slide",
        "state" : "contents",
        "slide" : "none"
      },
      "url" : {
        "native" : "assets\/E42D39F1-91E2-4E28-B0A5-E431EC188862.pdf"
      },
      "width" : 1024,
      "height" : 768
    }
  },
  "events" : [
    {
      "effects" : [
        {
          "beginTime" : 0,
          "baseLayer" : {
            "animations" : [

            ],
            "initialState" : {
              "affineTransform" : [
                1,
                0,
                0,
                1,
                0,
                0
              ],
              "masksToBounds" : false,
              "rotation" : 0,
              "scale" : 1,
              "position" : {
                "pointX" : 512,
                "pointY" : 384
              },
              "width" : 1024,
              "sublayerTransform" : [
                1,
                0,
                0,
                0,
                0,
                1,
                0,
                0,
                0,
                0,
                1,
                0,
                0,
                0,
                0,
                1
              ],
              "contentsRect" : {
                "y" : 0,
                "x" : 0,
                "width" : 1,
                "height" : 1
              },
              "opacity" : 1,
              "edgeAntialiasingMask" : 251658240,
              "height" : 768,
              "hidden" : false,
              "anchorPoint" : {
                "pointX" : 0.5,
                "pointY" : 0.5
              }
            },
            "objectID" : "0",
            "layers" : [
              {
                "animations" : [

                ],
                "initialState" : {
                  "affineTransform" : [
                    1,
                    0,
                    0,
                    1,
                    0,
                    0
                  ],
                  "masksToBounds" : false,
                  "rotation" : 0,
                  "scale" : 1,
                  "position" : {
                    "pointX" : 512,
                    "pointY" : 384
                  },
                  "width" : 1024,
                  "sublayerTransform" : [
                    1,
                    0,
                    0,
                    0,
                    0,
                    1,
                    0,
                    0,
                    0,
                    0,
                    1,
                    -0.00049229876906403734,
                    0,
                    0,
                    0,
                    1
                  ],
                  "contentsRect" : {
                    "y" : 0,
                    "x" : 0,
                    "width" : 1,
                    "height" : 1
                  },
                  "opacity" : 1,
                  "edgeAntialiasingMask" : 251658240,
                  "height" : 768,
                  "hidden" : false,
                  "anchorPoint" : {
                    "pointX" : 0.5,
                    "pointY" : 0.5
                  }
                },
                "layers" : [
                  {
                    "animations" : [

                    ],
                    "layers" : [

                    ],
                    "texturedRectangle" : {
                      "isBackgroundTexture" : false,
                      "singleTextureOpacity" : 1,
                      "textureType" : 0,
                      "textBaseline" : 0,
                      "textXHeight" : 0,
                      "isVerticalText" : false
                    },
                    "initialState" : {
                      "affineTransform" : [
                        1,
                        0,
                        0,
                        1,
                        0,
                        0
                      ],
                      "masksToBounds" : false,
                      "rotation" : 0,
                      "scale" : 1,
                      "position" : {
                        "pointX" : 512,
                        "pointY" : 384
                      },
                      "width" : 1024,
                      "sublayerTransform" : [
                        1,
                        0,
                        0,
                        0,
                        0,
                        1,
                        0,
                        0,
                        0,
                        0,
                        1,
                        0,
                        0,
                        0,
                        0,
                        1
                      ],
                      "contentsRect" : {
                        "y" : 0,
                        "x" : 0,
                        "width" : 1,
                        "height" : 1
                      },
                      "opacity" : 1,
                      "edgeAntialiasingMask" : 0,
                      "height" : 768,
                      "hidden" : false,
                      "anchorPoint" : {
                        "pointX" : 0.5,
                        "pointY" : 0.5
                      }
                    },
                    "texture" : "48119D83BDF27884EA3D9E61FE2DAACC"
                  },
                  {
                    "animations" : [
                      {
                        "timeOffset" : 0,
                        "from" : {
                          "scalar" : false
                        },
                        "beginTime" : 0,
                        "repeatCount" : 0,
                        "fillMode" : "both",
                        "property" : "hidden",
                        "autoreverses" : false,
                        "duration" : 0.01,
                        "to" : {
                          "scalar" : true
                        }
                      }
                    ],
                    "layers" : [

                    ],
                    "texturedRectangle" : {
                      "isBackgroundTexture" : false,
                      "singleTextureOpacity" : 1,
                      "textureType" : 0,
                      "textBaseline" : 0,
                      "textXHeight" : 0,
                      "isVerticalText" : false
                    },
                    "initialState" : {
                      "affineTransform" : [
                        1,
                        0,
                        0,
                        1,
                        0,
                        0
                      ],
                      "masksToBounds" : false,
                      "rotation" : 0,
                      "scale" : 1,
                      "position" : {
                        "pointX" : 512,
                        "pointY" : 384
                      },
                      "width" : 1024,
                      "sublayerTransform" : [
                        1,
                        0,
                        0,
                        0,
                        0,
                        1,
                        0,
                        0,
                        0,
                        0,
                        1,
                        0,
                        0,
                        0,
                        0,
                        1
                      ],
                      "contentsRect" : {
                        "y" : 0,
                        "x" : 0,
                        "width" : 1,
                        "height" : 1
                      },
                      "opacity" : 1,
                      "edgeAntialiasingMask" : 0,
                      "height" : 768,
                      "hidden" : false,
                      "anchorPoint" : {
                        "pointX" : 0.5,
                        "pointY" : 0.5
                      }
                    },
                    "texture" : "B64F7886CD8D2F544D0273D8C8664C9C"
                  }
                ]
              }
            ]
          },
          "effects" : [

          ],
          "duration" : 0.01,
          "type" : "transition",
          "name" : "none",
          "objectID" : "0"
        }
      ],
      "automaticPlay" : false,
      "hyperlinks" : [

      ],
      "accessibility" : [
        {
          "text" : "After",
          "targetRectangle" : {
            "y" : 149.42276000976562,
            "x" : 824.3936767578125,
            "width" : 57.149999999999977,
            "height" : 39.000117588038847
          }
        },
        {
          "text" : "Interactive Snapshot Mode",
          "targetRectangle" : {
            "y" : 31.557765960693359,
            "x" : 95.413818359375,
            "width" : 821.67800000000011,
            "height" : 114.81634649656917
          }
        },
        {
          "text" : "int-after-1.png",
          "targetRectangle" : {
            "y" : 102.771484375,
            "x" : 63.90057373046875,
            "width" : 900.1988525390625,
            "height" : 682
          }
        }
      ],
      "baseLayer" : {
        "animations" : [

        ],
        "initialState" : {
          "affineTransform" : [
            1,
            0,
            0,
            1,
            0,
            0
          ],
          "masksToBounds" : false,
          "rotation" : 0,
          "scale" : 1,
          "position" : {
            "pointX" : 512,
            "pointY" : 384
          },
          "width" : 1024,
          "sublayerTransform" : [
            1,
            0,
            0,
            0,
            0,
            1,
            0,
            0,
            0,
            0,
            1,
            0,
            0,
            0,
            0,
            1
          ],
          "contentsRect" : {
            "y" : 0,
            "x" : 0,
            "width" : 1,
            "height" : 1
          },
          "opacity" : 1,
          "edgeAntialiasingMask" : 251658240,
          "height" : 768,
          "hidden" : false,
          "anchorPoint" : {
            "pointX" : 0.5,
            "pointY" : 0.5
          }
        },
        "objectID" : "0",
        "layers" : [
          {
            "animations" : [

            ],
            "initialState" : {
              "affineTransform" : [
                1,
                0,
                0,
                1,
                0,
                0
              ],
              "masksToBounds" : false,
              "rotation" : 0,
              "scale" : 1,
              "position" : {
                "pointX" : 512,
                "pointY" : 384
              },
              "width" : 1024,
              "sublayerTransform" : [
                1,
                0,
                0,
                0,
                0,
                1,
                0,
                0,
                0,
                0,
                1,
                0,
                0,
                0,
                0,
                1
              ],
              "contentsRect" : {
                "y" : 0,
                "x" : 0,
                "width" : 1,
                "height" : 1
              },
              "opacity" : 1,
              "edgeAntialiasingMask" : 251658240,
              "height" : 768,
              "hidden" : false,
              "anchorPoint" : {
                "pointX" : 0.5,
                "pointY" : 0.5
              }
            },
            "layers" : [
              {
                "animations" : [

                ],
                "initialState" : {
                  "affineTransform" : [
                    1,
                    0,
                    0,
                    1,
                    0,
                    0
                  ],
                  "masksToBounds" : false,
                  "rotation" : 0,
                  "scale" : 1,
                  "position" : {
                    "pointX" : 512,
                    "pointY" : 384
                  },
                  "width" : 1024,
                  "sublayerTransform" : [
                    1,
                    0,
                    0,
                    0,
                    0,
                    1,
                    0,
                    0,
                    0,
                    0,
                    1,
                    0,
                    0,
                    0,
                    0,
                    1
                  ],
                  "contentsRect" : {
                    "y" : 0,
                    "x" : 0,
                    "width" : 1,
                    "height" : 1
                  },
                  "opacity" : 1,
                  "edgeAntialiasingMask" : 251658240,
                  "height" : 768,
                  "hidden" : false,
                  "anchorPoint" : {
                    "pointX" : 0.5,
                    "pointY" : 0.5
                  }
                },
                "layers" : [
                  {
                    "animations" : [

                    ],
                    "layers" : [

                    ],
                    "texturedRectangle" : {
                      "isBackgroundTexture" : true,
                      "singleTextureOpacity" : 1,
                      "textureType" : 1,
                      "textBaseline" : 0,
                      "textXHeight" : 0,
                      "isVerticalText" : false
                    },
                    "initialState" : {
                      "affineTransform" : [
                        1,
                        0,
                        0,
                        1,
                        0,
                        0
                      ],
                      "masksToBounds" : false,
                      "rotation" : 0,
                      "scale" : 1,
                      "position" : {
                        "pointX" : 512,
                        "pointY" : 384
                      },
                      "width" : 1024,
                      "sublayerTransform" : [
                        1,
                        0,
                        0,
                        0,
                        0,
                        1,
                        0,
                        0,
                        0,
                        0,
                        1,
                        0,
                        0,
                        0,
                        0,
                        1
                      ],
                      "contentsRect" : {
                        "y" : 0,
                        "x" : 0,
                        "width" : 1,
                        "height" : 1
                      },
                      "opacity" : 1,
                      "edgeAntialiasingMask" : 0,
                      "height" : 768,
                      "hidden" : false,
                      "anchorPoint" : {
                        "pointX" : 0.5,
                        "pointY" : 0.5
                      }
                    },
                    "texture" : "FBB5DEA59905EE30EF2803B0A74DF992"
                  }
                ]
              }
            ]
          },
          {
            "animations" : [

            ],
            "initialState" : {
              "affineTransform" : [
                1,
                0,
                0,
                1,
                0,
                0
              ],
              "masksToBounds" : false,
              "rotation" : 0,
              "scale" : 1,
              "position" : {
                "pointX" : 512,
                "pointY" : 384
              },
              "width" : 1024,
              "sublayerTransform" : [
                1,
                0,
                0,
                0,
                0,
                1,
                0,
                0,
                0,
                0,
                1,
                0,
                0,
                0,
                0,
                1
              ],
              "contentsRect" : {
                "y" : 0,
                "x" : 0,
                "width" : 1,
                "height" : 1
              },
              "opacity" : 1,
              "edgeAntialiasingMask" : 251658240,
              "height" : 768,
              "hidden" : false,
              "anchorPoint" : {
                "pointX" : 0.5,
                "pointY" : 0.5
              }
            },
            "layers" : [
              {
                "animations" : [

                ],
                "initialState" : {
                  "affineTransform" : [
                    1,
                    0,
                    0,
                    1,
                    0,
                    0
                  ],
                  "masksToBounds" : false,
                  "rotation" : 0,
                  "scale" : 1,
                  "position" : {
                    "pointX" : 503.413818359375,
                    "pointY" : 124.55776596069336
                  },
                  "width" : 824,
                  "sublayerTransform" : [
                    1,
                    0,
                    0,
                    0,
                    0,
                    1,
                    0,
                    0,
                    0,
                    0,
                    1,
                    0,
                    0,
                    0,
                    0,
                    1
                  ],
                  "contentsRect" : {
                    "y" : 0,
                    "x" : 0,
                    "width" : 1,
                    "height" : 1
                  },
                  "opacity" : 1,
                  "edgeAntialiasingMask" : 251658240,
                  "height" : 198,
                  "hidden" : false,
                  "anchorPoint" : {
                    "pointX" : 0.5,
                    "pointY" : 0.5
                  }
                },
                "layers" : [
                  {
                    "animations" : [

                    ],
                    "layers" : [

                    ],
                    "texturedRectangle" : {
                      "singleTextureOpacity" : 1,
                      "textXHeight" : 0.22635757575757579,
                      "textBaseline" : 1.6687448765917159,
                      "isBackgroundTexture" : true,
                      "isVerticalText" : false,
                      "textColor" : [
                        0.51372557878494263,
                        0.52941179275512695,
                        0.52941173315048218,
                        1
                      ],
                      "textureType" : 6
                    },
                    "initialState" : {
                      "affineTransform" : [
                        1,
                        0,
                        0,
                        1,
                        0,
                        0
                      ],
                      "masksToBounds" : false,
                      "rotation" : 0,
                      "scale" : 1,
                      "position" : {
                        "pointX" : 415.586181640625,
                        "pointY" : 102.44223403930664
                      },
                      "width" : 824,
                      "sublayerTransform" : [
                        1,
                        0,
                        0,
                        0,
                        0,
                        1,
                        0,
                        0,
                        0,
                        0,
                        1,
                        0,
                        0,
                        0,
                        0,
                        1
                      ],
                      "contentsRect" : {
                        "y" : 0,
                        "x" : 0,
                        "width" : 1,
                        "height" : 1
                      },
                      "opacity" : 1,
                      "edgeAntialiasingMask" : 0,
                      "height" : 198,
                      "hidden" : false,
                      "anchorPoint" : {
                        "pointX" : 0.5,
                        "pointY" : 0.5
                      }
                    },
                    "texture" : "D0D8472915A570F5F53611B33B594150"
                  }
                ]
              }
            ]
          },
          {
            "animations" : [

            ],
            "initialState" : {
              "affineTransform" : [
                1,
                0,
                0,
                1,
                0,
                0
              ],
              "masksToBounds" : false,
              "rotation" : 0,
              "scale" : 1,
              "position" : {
                "pointX" : 512,
                "pointY" : 384
              },
              "width" : 1024,
              "sublayerTransform" : [
                1,
                0,
                0,
                0,
                0,
                1,
                0,
                0,
                0,
                0,
                1,
                0,
                0,
                0,
                0,
                1
              ],
              "contentsRect" : {
                "y" : 0,
                "x" : 0,
                "width" : 1,
                "height" : 1
              },
              "opacity" : 1,
              "edgeAntialiasingMask" : 251658240,
              "height" : 768,
              "hidden" : false,
              "anchorPoint" : {
                "pointX" : 0.5,
                "pointY" : 0.5
              }
            },
            "layers" : [
              {
                "animations" : [

                ],
                "initialState" : {
                  "affineTransform" : [
                    1,
                    0,
                    0,
                    1,
                    0,
                    0
                  ],
                  "masksToBounds" : false,
                  "rotation" : 0,
                  "scale" : 1,
                  "position" : {
                    "pointX" : 515.90057373046875,
                    "pointY" : 445.271484375
                  },
                  "width" : 904,
                  "sublayerTransform" : [
                    1,
                    0,
                    0,
                    0,
                    0,
                    1,
                    0,
                    0,
                    0,
                    0,
                    1,
                    0,
                    0,
                    0,
                    0,
                    1
                  ],
                  "contentsRect" : {
                    "y" : 0,
                    "x" : 0,
                    "width" : 1,
                    "height" : 1
                  },
                  "opacity" : 1,
                  "edgeAntialiasingMask" : 251658240,
                  "height" : 685,
                  "hidden" : false,
                  "anchorPoint" : {
                    "pointX" : 0.5,
                    "pointY" : 0.5
                  }
                },
                "layers" : [
                  {
                    "animations" : [

                    ],
                    "layers" : [

                    ],
                    "texturedRectangle" : {
                      "isBackgroundTexture" : true,
                      "singleTextureOpacity" : 1,
                      "textureType" : 5,
                      "textBaseline" : 0,
                      "textXHeight" : 0,
                      "isVerticalText" : false
                    },
                    "initialState" : {
                      "affineTransform" : [
                        1,
                        0,
                        0,
                        1,
                        0,
                        0
                      ],
                      "masksToBounds" : false,
                      "rotation" : 0,
                      "scale" : 1,
                      "position" : {
                        "pointX" : 450.09942626953125,
                        "pointY" : 340.728515625
                      },
                      "width" : 904,
                      "sublayerTransform" : [
                        1,
                        0,
                        0,
                        0,
                        0,
                        1,
                        0,
                        0,
                        0,
                        0,
                        1,
                        0,
                        0,
                        0,
                        0,
                        1
                      ],
                      "contentsRect" : {
                        "y" : 0,
                        "x" : 0,
                        "width" : 1,
                        "height" : 1
                      },
                      "opacity" : 1,
                      "edgeAntialiasingMask" : 0,
                      "height" : 685,
                      "hidden" : false,
                      "anchorPoint" : {
                        "pointX" : 0.5,
                        "pointY" : 0.5
                      }
                    },
                    "texture" : "4A1547C44D2F609A82737A690921C3FB"
                  }
                ]
              }
            ]
          },
          {
            "animations" : [

            ],
            "initialState" : {
              "affineTransform" : [
                1,
                0,
                0,
                1,
                0,
                0
              ],
              "masksToBounds" : false,
              "rotation" : 0,
              "scale" : 1,
              "position" : {
                "pointX" : 512,
                "pointY" : 384
              },
              "width" : 1024,
              "sublayerTransform" : [
                1,
                0,
                0,
                0,
                0,
                1,
                0,
                0,
                0,
                0,
                1,
                0,
                0,
                0,
                0,
                1
              ],
              "contentsRect" : {
                "y" : 0,
                "x" : 0,
                "width" : 1,
                "height" : 1
              },
              "opacity" : 1,
              "edgeAntialiasingMask" : 251658240,
              "height" : 768,
              "hidden" : false,
              "anchorPoint" : {
                "pointX" : 0.5,
                "pointY" : 0.5
              }
            },
            "layers" : [
              {
                "animations" : [

                ],
                "initialState" : {
                  "affineTransform" : [
                    1,
                    0,
                    0,
                    1,
                    0,
                    0
                  ],
                  "masksToBounds" : false,
                  "rotation" : 0,
                  "scale" : 1,
                  "position" : {
                    "pointX" : 850.8936767578125,
                    "pointY" : 157.92276000976562
                  },
                  "width" : 61,
                  "sublayerTransform" : [
                    1,
                    0,
                    0,
                    0,
                    0,
                    1,
                    0,
                    0,
                    0,
                    0,
                    1,
                    0,
                    0,
                    0,
                    0,
                    1
                  ],
                  "contentsRect" : {
                    "y" : 0,
                    "x" : 0,
                    "width" : 1,
                    "height" : 1
                  },
                  "opacity" : 1,
                  "edgeAntialiasingMask" : 251658240,
                  "height" : 25,
                  "hidden" : false,
                  "anchorPoint" : {
                    "pointX" : 0.5,
                    "pointY" : 0.5
                  }
                },
                "layers" : [
                  {
                    "animations" : [

                    ],
                    "layers" : [

                    ],
                    "texturedRectangle" : {
                      "singleTextureOpacity" : 1,
                      "textXHeight" : 0.60839999999999994,
                      "textBaseline" : -0.103089599609375,
                      "isBackgroundTexture" : true,
                      "isVerticalText" : false,
                      "textColor" : [
                        0.2039216160774231,
                        0.64705884456634521,
                        0.85490202903747559,
                        1
                      ],
                      "textureType" : 6
                    },
                    "initialState" : {
                      "affineTransform" : [
                        1,
                        0,
                        0,
                        1,
                        0,
                        0
                      ],
                      "masksToBounds" : false,
                      "rotation" : 0,
                      "scale" : 1,
                      "position" : {
                        "pointX" : 33.1063232421875,
                        "pointY" : 15.077239990234375
                      },
                      "width" : 61,
                      "sublayerTransform" : [
                        1,
                        0,
                        0,
                        0,
                        0,
                        1,
                        0,
                        0,
                        0,
                        0,
                        1,
                        0,
                        0,
                        0,
                        0,
                        1
                      ],
                      "contentsRect" : {
                        "y" : 0,
                        "x" : 0,
                        "width" : 1,
                        "height" : 1
                      },
                      "opacity" : 1,
                      "edgeAntialiasingMask" : 0,
                      "height" : 25,
                      "hidden" : false,
                      "anchorPoint" : {
                        "pointX" : 0.5,
                        "pointY" : 0.5
                      }
                    },
                    "texture" : "864A7B7723CE1A8CF60C01BEC0876FB0"
                  }
                ]
              }
            ]
          }
        ]
      }
    }
  ]
}